hashedindex/__init__.py
hashedindex/textparser.py
hashedindex-0.10.0.dist-info/AUTHORS.rst
hashedindex-0.10.0.dist-info/LICENSE
hashedindex-0.10.0.dist-info/METADATA
hashedindex-0.10.0.dist-info/WHEEL
hashedindex-0.10.0.dist-info/top_level.txt
hashedindex-0.10.0.dist-info/RECORD
