Metadata-Version: 2.1
Name: hashedindex
Version: 0.10.0
Summary: InvertedIndex implementation using hash lists (dictionaries)
Home-page: https://github.com/MichaelAquilina/hashedindex
Author: Michael Aquilina
Author-email: michaelaquilina@gmail.com
License: BSD
Keywords: hashedindex
Platform: UNKNOWN
Classifier: Development Status :: 2 - Pre-Alpha
Classifier: Intended Audience :: Developers
Classifier: License :: OSI Approved :: BSD License
Classifier: Natural Language :: English
Classifier: Programming Language :: Python :: 3.5
Classifier: Programming Language :: Python :: 3.6
Classifier: Programming Language :: Python :: 3.7
Classifier: Programming Language :: Python :: 3.8
